gcf/__init__.py
gcf/functions/__init__.py
gcf/functions/dispatch/__init__.py
gcf/functions/dispatch/events.py
gcf/functions/dispatch/execution.py
gcf/functions/dispatch/tasks.py
gcf/functions/execution/__init__.py
gcf/functions/execution/config.py
gcf/functions/execution/exceptions.py
gcf/functions/execution/execution.py
gcf/functions/execution/functions.py
gcf/functions/execution/progress.py
gcf/functions/execution/threading.py
gcf/functions/execution/time.py
gcf/functions/execution/worker.py
gcf/functions/execution/events/__init__.py
gcf/functions/execution/events/events.py
gcf/functions/execution/events/handler.py
gcf/functions/workflow/__init__.py
gcf/functions/workflow/events.py
gcf/functions/workflow/execution.py
gcf/functions/workflow/tasks.py
gcf_cloud_functions-1.0.29.dist-info/LICENSE
gcf_cloud_functions-1.0.29.dist-info/METADATA
gcf_cloud_functions-1.0.29.dist-info/WHEEL
gcf_cloud_functions-1.0.29.dist-info/top_level.txt
gcf_cloud_functions-1.0.29.dist-info/RECORD
